shongololo/Imet_serial.py
shongololo/K30_serial.py
shongololo/__init__.py
shongololo/default_settings.py
shongololo/shongololo.py
shongololo/start_up.py
shongololo/sys_admin.py
shongololo-1.1.0.dist-info/METADATA
shongololo-1.1.0.dist-info/RECORD
shongololo-1.1.0.dist-info/WHEEL
shongololo-1.1.0.dist-info/top_level.txt
