Metadata-Version: 2.1
Name: shongololo
Version: 1.1.0
Summary: Python application for simply sensor data capture on a Pi
Home-page: https://gitlab.com/r4space/VTAgMonitoring/tree/master/code/shongololos
Author: J Wyngaard
Author-email: r4space@gmail.com
License: UNKNOWN
Platform: UNKNOWN
Classifier: Programming Language :: Python :: 3
Classifier: License :: OSI Approved :: Apache Software License
Classifier: Operating System :: POSIX
Requires-Dist: serial
Requires-Dist: pyserial
Requires-Dist: simple-settings
